LICENSE.txt
MANIFEST.in
README.md
README.rst
requirements.txt
setup.cfg
setup.py
multidb_admin/__init__.py
multidb_admin/admin.py
multidb_admin/apps.py
multidb_admin/middleware.py
multidb_admin/router.py
multidb_admin/tests.py
sample_test_package.egg-info/PKG-INFO
sample_test_package.egg-info/SOURCES.txt
sample_test_package.egg-info/dependency_links.txt
sample_test_package.egg-info/requires.txt
sample_test_package.egg-info/top_level.txt
waffle_project/__init__.py
waffle_project/asgi.py
waffle_project/settings.py
waffle_project/urls.py
waffle_project/wsgi.py