Metadata-Version: 2.1
Name: sample-test-package
Version: 1.5.0
Summary: Sample Test Package 
Home-page: https://github.com/pys-info/pys-issue-tracker
Author: Suraj Patidar
Author-email: suraj.pysquad@gmail.com
Project-URL: Bug Reports, https://github.com/pys-info/pys-issue-tracker/issues
Project-URL: Source, https://github.com/pys-info/pys-issue-tracker
Keywords: django,issue,tracker,development
Classifier: Development Status :: 5 - Production/Stable
Classifier: Intended Audience :: Developers
Classifier: Topic :: Software Development :: Build Tools
Classifier: License :: OSI Approved :: MIT License
Classifier: Environment :: Web Environment
Classifier: Operating System :: OS Independent
Classifier: Programming Language :: Python :: 3.5
Classifier: Programming Language :: Python :: 3.6
Classifier: Programming Language :: Python :: 3.7
Classifier: Programming Language :: Python :: 3.8
Classifier: Programming Language :: Python :: 3.9
Classifier: Programming Language :: Python :: 3.10
Classifier: Programming Language :: Python :: 3 :: Only
Classifier: Framework :: Django
Classifier: Framework :: Django :: 3.0
Classifier: Framework :: Django :: 3.1
Classifier: Framework :: Django :: 3.2
Classifier: Framework :: Django :: 4.0
Classifier: Framework :: Django :: 4.1
Classifier: Framework :: Django :: 4.2
Requires-Python: >=3.5
Provides-Extra: celery
Provides-Extra: django
Provides-Extra: flask
License-File: LICENSE.txt
